client/__init__.py
client/client.py
client/client/__init__.py
client/client/add_contact.py
client/client/client_database.py
client/client/del_contact.py
client/client/main_window.py
client/client/main_window_conv.py
client/client/start_dialog.py
client/client/transport.py
client/common/__init__.py
client/common/decos.py
client/common/descriptors.py
client/common/errors_user.py
client/common/metaclasses.py
client/common/utils.py
client/common/variables.py
client/logs/__init__.py
client/logs/client_logs_config.py
client/logs/server_logs_config.py
client/unit_tests/__init__.py
client/unit_tests/test_client.py
client/unit_tests/test_utils.py
PythonProj_Message_Client-0.0.1.dist-info/METADATA
PythonProj_Message_Client-0.0.1.dist-info/WHEEL
PythonProj_Message_Client-0.0.1.dist-info/top_level.txt
PythonProj_Message_Client-0.0.1.dist-info/RECORD
