Metadata-Version: 2.1
Name: PythonProj-Message-Client
Version: 0.0.1
Summary: Message real_client from SergeyZ
Home-page: UNKNOWN
Author: Sergey Zubkov
Author-email: zo0zo0@mail.ru
License: UNKNOWN
Platform: UNKNOWN
Requires-Dist: PyQt5
Requires-Dist: sqlalchemy
Requires-Dist: pycryptodome
Requires-Dist: pycryptodomex
